py_flux_tracer/__init__.py
py_flux_tracer/campbell/eddy_data_figures_generator.py
py_flux_tracer/campbell/eddy_data_preprocessor.py
py_flux_tracer/campbell/spectrum_calculator.py
py_flux_tracer/commons/utilities.py
py_flux_tracer/footprint/flux_footprint_analyzer.py
py_flux_tracer/mobile/correcting_utils.py
py_flux_tracer/mobile/hotspot_emission_analyzer.py
py_flux_tracer/mobile/mobile_measurement_analyzer.py
py_flux_tracer/monthly/monthly_converter.py
py_flux_tracer/monthly/monthly_figures_generator.py
py_flux_tracer/transfer_function/fft_files_reorganizer.py
py_flux_tracer/transfer_function/transfer_function_calculator.py
py_flux_tracer-1.0.0.dist-info/METADATA
py_flux_tracer-1.0.0.dist-info/WHEEL
py_flux_tracer-1.0.0.dist-info/licenses/LICENSE
py_flux_tracer-1.0.0.dist-info/RECORD
