Metadata-Version: 2.4
Name: py-flux-tracer
Version: 1.0.0
Summary: This package provides methods for analyzing atmospheric observation data, primarily eddy covariance methods.
Project-URL: Homepage, https://github.com/connect0459/py-flux-tracer
Project-URL: Bug Tracker, https://github.com/connect0459/py-flux-tracer/issues
Author-email: connect0459 <connect0459@gmail.com>
License-Expression: MIT
License-File: LICENSE
Keywords: covariance,eddy,ethane,flux,footprint,hotspots,meteorology,methane,spectrum
Classifier: Development Status :: 3 - Alpha
Classifier: Intended Audience :: Science/Research
Classifier: License :: OSI Approved :: MIT License
Classifier: Programming Language :: Python :: 3
Classifier: Programming Language :: Python :: 3.11
Classifier: Topic :: Scientific/Engineering :: Atmospheric Science
Requires-Python: >=3.11
Requires-Dist: folium>=0.18.0
Requires-Dist: geopy>=2.4.1
Requires-Dist: jpholiday
Requires-Dist: matplotlib
Requires-Dist: nbformat>=5.10.4
Requires-Dist: numpy
Requires-Dist: openpyxl>=3.1.5
Requires-Dist: pandas
Requires-Dist: pillow
Requires-Dist: plotly>=5.24.1
Requires-Dist: scipy
Requires-Dist: setuptools-scm
Requires-Dist: tqdm
